shufflers/__init__.py
shufflers/cli.py
shufflers/models/__init__.py
shufflers/models/shufflelm.py
shufflers/models/fasterdecodemixer/__init__.py
shufflers/models/fasterdecodemixer/mixer.py
shufflers/models/fasterdecodemixer/model.py
shufflers/models/fasterdecodemixer/rotary.py
shufflers/utils/__init__.py
shufflers/utils/config.py
shufflers/utils/generation.py
shufflers/utils/tokenizer.py
shufflers/utils/visualization.py
shufflers-0.1.0.dist-info/entry_points.txt
shufflers-0.1.0.dist-info/licenses/LICENSE
shufflers-0.1.0.dist-info/WHEEL
shufflers-0.1.0.dist-info/METADATA
shufflers-0.1.0.dist-info/RECORD
