Metadata-Version: 2.4
Name: shufflers
Version: 0.1.0
Summary: ShuffleLM: Parallel Token Generation Language Models with Intelligent Reordering
Keywords: language-model,transformer,mlp-mixer,parallel-generation,natural-language-processing,deep-learning,pytorch,shufflelm,rotary-regression
Author-email: thisisthepy <thisisthepy@gmail.com>
Requires-Python: >=3.9
Classifier: Development Status :: 4 - Beta
Classifier: Intended Audience :: Developers
Classifier: Intended Audience :: Science/Research
Classifier: License :: OSI Approved :: MIT License
Classifier: Operating System :: OS Independent
Classifier: Programming Language :: Python :: 3
Classifier: Programming Language :: Python :: 3.9
Classifier: Programming Language :: Python :: 3.10
Classifier: Programming Language :: Python :: 3.11
Classifier: Programming Language :: Python :: 3.12
Classifier: Programming Language :: Python :: 3.13
Classifier: Topic :: Scientific/Engineering :: Artificial Intelligence
Classifier: Topic :: Software Development :: Libraries :: Python Modules
Classifier: Topic :: Text Processing :: Linguistic
License-File: LICENSE
Requires-Dist: torch>=2.0.0
Requires-Dist: transformers>=4.21.0
Requires-Dist: numpy>=1.21.0
Requires-Dist: einops>=0.6.0
Requires-Dist: tqdm>=4.64.0
Requires-Dist: safetensors>=0.3.0
Requires-Dist: tokenizers>=0.13.0
Requires-Dist: huggingface-hub>=0.16.0
Requires-Dist: packaging>=21.0
Requires-Dist: shufflers[dev, docs, visualization, benchmark] ; extra == "all"
Requires-Dist: datasets>=2.0.0 ; extra == "benchmark"
Requires-Dist: evaluate>=0.4.0 ; extra == "benchmark"
Requires-Dist: wandb>=0.13.0 ; extra == "benchmark"
Requires-Dist: accelerate>=0.20.0 ; extra == "benchmark"
Requires-Dist: pytest>=7.0.0 ; extra == "dev"
Requires-Dist: pytest-cov>=4.0.0 ; extra == "dev"
Requires-Dist: pytest-xdist>=3.0.0 ; extra == "dev"
Requires-Dist: black>=23.0.0 ; extra == "dev"
Requires-Dist: isort>=5.12.0 ; extra == "dev"
Requires-Dist: flake8>=6.0.0 ; extra == "dev"
Requires-Dist: mypy>=1.0.0 ; extra == "dev"
Requires-Dist: pre-commit>=3.0.0 ; extra == "dev"
Requires-Dist: sphinx>=5.0.0 ; extra == "docs"
Requires-Dist: sphinx-rtd-theme>=1.2.0 ; extra == "docs"
Requires-Dist: myst-parser>=0.18.0 ; extra == "docs"
Requires-Dist: sphinx-autodoc-typehints>=1.19.0 ; extra == "docs"
Requires-Dist: matplotlib>=3.5.0 ; extra == "visualization"
Requires-Dist: seaborn>=0.11.0 ; extra == "visualization"
Requires-Dist: plotly>=5.0.0 ; extra == "visualization"
Requires-Dist: pillow>=9.0.0 ; extra == "visualization"
Requires-Dist: imageio>=2.22.0 ; extra == "visualization"
Project-URL: Bug Tracker, https://github.com/thisisthepy/ShuffleLM/issues
Project-URL: Changelog, https://github.com/thisisthepy/ShuffleLM/blob/main/CHANGELOG.md
Project-URL: Discussions, https://github.com/thisisthepy/ShuffleLM/discussions
Project-URL: Documentation, https://shufflelm.readthedocs.io
Project-URL: Homepage, https://github.com/thisisthepy/ShuffleLM
Project-URL: Repository, https://github.com/thisisthepy/ShuffleLM
Provides-Extra: all
Provides-Extra: benchmark
Provides-Extra: dev
Provides-Extra: docs
Provides-Extra: visualization
